ManyQt/QAxContainer.py
ManyQt/Qsci.py
ManyQt/Qt3DAnimation.py
ManyQt/Qt3DCore.py
ManyQt/Qt3DExtras.py
ManyQt/Qt3DInput.py
ManyQt/Qt3DLogic.py
ManyQt/Qt3DRender.py
ManyQt/QtAsyncio.py
ManyQt/QtAxContainer.py
ManyQt/QtBluetooth.py
ManyQt/QtChart.py
ManyQt/QtCharts.py
ManyQt/QtConcurrent.py
ManyQt/QtCore.py
ManyQt/QtDBus.py
ManyQt/QtDataVisualization.py
ManyQt/QtDesigner.py
ManyQt/QtGraphs.py
ManyQt/QtGraphsWidgets.py
ManyQt/QtGui.py
ManyQt/QtHelp.py
ManyQt/QtHttpServer.py
ManyQt/QtLocation.py
ManyQt/QtMacExtras.py
ManyQt/QtMultimedia.py
ManyQt/QtMultimediaWidgets.py
ManyQt/QtNetwork.py
ManyQt/QtNetworkAuth.py
ManyQt/QtNfc.py
ManyQt/QtOpenGL.py
ManyQt/QtOpenGLWidgets.py
ManyQt/QtPdf.py
ManyQt/QtPdfWidgets.py
ManyQt/QtPositioning.py
ManyQt/QtPrintSupport.py
ManyQt/QtPurchasing.py
ManyQt/QtQml.py
ManyQt/QtQuick.py
ManyQt/QtQuick3D.py
ManyQt/QtQuickControls2.py
ManyQt/QtQuickWidgets.py
ManyQt/QtRemoteObjects.py
ManyQt/QtScxml.py
ManyQt/QtSensors.py
ManyQt/QtSerialBus.py
ManyQt/QtSerialPort.py
ManyQt/QtSpatialAudio.py
ManyQt/QtSql.py
ManyQt/QtStateMachine.py
ManyQt/QtSvg.py
ManyQt/QtSvgWidgets.py
ManyQt/QtTest.py
ManyQt/QtTextToSpeech.py
ManyQt/QtUiTools.py
ManyQt/QtVirtualKeyboard.py
ManyQt/QtWebChannel.py
ManyQt/QtWebEngineCore.py
ManyQt/QtWebEngineQuick.py
ManyQt/QtWebEngineWidgets.py
ManyQt/QtWebKit.py
ManyQt/QtWebKitWidgets.py
ManyQt/QtWebSockets.py
ManyQt/QtWebView.py
ManyQt/QtWidgets.py
ManyQt/QtWinExtras.py
ManyQt/QtX11Extras.py
ManyQt/QtXml.py
ManyQt/QtXmlPatterns.py
ManyQt/__init__.py
ManyQt/__main__.py
ManyQt/_api.py
ManyQt/_compat.py
ManyQt/_ctypes.py
ManyQt/_fixes.py
ManyQt/cli.py
ManyQt/importhooks.py
ManyQt/shiboken.py
ManyQt/sip.py
ManyQt/uic.py
ManyQt/_backport/QtCore.py
ManyQt/_backport/QtDBus.py
ManyQt/_backport/QtDesigner.py
ManyQt/_backport/QtGui.py
ManyQt/_backport/QtHelp.py
ManyQt/_backport/QtMultimedia.py
ManyQt/_backport/QtNetwork.py
ManyQt/_backport/QtOpenGL.py
ManyQt/_backport/QtSql.py
ManyQt/_backport/QtSvg.py
ManyQt/_backport/QtTest.py
ManyQt-0.3.3.dist-info/LICENSE.txt
ManyQt-0.3.3.dist-info/METADATA
ManyQt-0.3.3.dist-info/WHEEL
ManyQt-0.3.3.dist-info/top_level.txt
ManyQt-0.3.3.dist-info/RECORD
