Metadata-Version: 2.2
Name: ManyQt
Version: 0.3.3
Summary: PyQt/PySide compatibility layer.
Author: UsamaTN
License: GPLv3
Keywords: GUI,PyQt4,PyQt5,PyQt6,PySide,PySide2,PySide6,compatibility
Classifier: Development Status :: 1 - Planning
Classifier: Intended Audience :: Developers
Classifier: License :: OSI Approved :: GNU General Public License v3 (GPLv3)
Classifier: Operating System :: OS Independent
Classifier: Programming Language :: Python :: 2
Classifier: Programming Language :: Python :: 3
License-File: LICENSE.txt
Dynamic: author
Dynamic: classifier
Dynamic: description
Dynamic: keywords
Dynamic: license
Dynamic: summary
